kimina/__init__.py
kimina/async_client.py
kimina/base.py
kimina/client_old.py
kimina/infotree.py
kimina/models.py
kimina/proof_utils.py
kimina/py.typed
kimina/sync_client.py
kimina-0.1.2.dist-info/METADATA
kimina-0.1.2.dist-info/WHEEL
kimina-0.1.2.dist-info/licenses/LICENSE
kimina-0.1.2.dist-info/RECORD
